smart_covdefaults/__init__.py
smart_covdefaults/defaults.py
smart_covdefaults/plugin.py
smart_covdefaults/version_util.py
smart_covdefaults/exclusion/__init__.py
smart_covdefaults/exclusion/conditional.py
smart_covdefaults/exclusion/plaform_based.py
smart_covdefaults/exclusion/py_version.py
smart_covdefaults-0.1.0.dist-info/licenses/LICENSE
smart_covdefaults-0.1.0.dist-info/METADATA
smart_covdefaults-0.1.0.dist-info/WHEEL
smart_covdefaults-0.1.0.dist-info/top_level.txt
smart_covdefaults-0.1.0.dist-info/RECORD
