Metadata-Version: 2.4
Name: smart-covdefaults
Version: 0.1.0
Summary: A better version of asottile's covdefaults.
Requires-Python: >=3.10
License-File: LICENSE
Requires-Dist: coverage>=7.10.6
Dynamic: license-file
